{
  "source": "Chy (COO/CRO/CFO) — populated 2026-04-10",
  "note": "Wire these into 777 v2 sections. Also pull live from TOS spreadsheet + APIs.",

  "revenue": {
    "mrr": 4200,
    "mrr_target_eoy": 50000,
    "arr_projected": 50400,
    "customer_count": 25,
    "pipeline": 150,
    "churn_rate": 0,
    "avg_revenue_per_customer": 168,
    "ltv_cac_ratio": "225:1",
    "net_new_mrr_this_month": 0,
    "tiers": {
      "$149": 0,
      "$499": 0,
      "$999": 0,
      "enterprise": 0
    }
  },

  "investor_pipeline": {
    "total_investors": 97,
    "outreach": 70,
    "email_sent": 25,
    "portal_visited": 1,
    "gift_opened": 7,
    "return_visitors": 8,
    "call_scheduled": 0,
    "invested": 0,
    "api_endpoints": {
      "crm_stats": "/api/crm/stats",
      "investor_analytics": "/api/investor-analytics",
      "tracking_file": "investor-tracking.jsonl"
    }
  },

  "financial_health": {
    "seed2_raised": 332500,
    "seed2_target": 2500000,
    "seed2_pct": 13.3,
    "debt_legacy": 359000,
    "pre_money_valuation": 55000000,
    "makr_investment": 25000000,
    "makr_valuation": 105000000,
    "breakeven_months": "3-4",
    "note": "Cash position and burn rate need manual input from Jared"
  },

  "meeting_schedule": {
    "total_meetings": 6,
    "async_sync": true,
    "schedule_url": "https://purebrain.ai/meeting-strategy/",
    "agendas_url": "https://purebrain.ai/meetings/"
  },

  "spreadsheet_ids": {
    "tos_dashboard": "1bMshOr-Hf4PVh2fycj0t7U_rBxByzD-FyBdEoVRMgEs",
    "team_whitelist": "1HALg8Vxu-LtS6OVq_CeO1gT4vFBUKxjtyKpJcTKM_0E",
    "personal_777": "1HuJIWEEXpkHgpL2iI6Zit9_cxw3dNd_8zZkOzsK4BGk",
    "investor_tracking": "1j5nT0f3wVbf"
  }
}
